README.rst
setup.py
pyminidict/dictionary.py
pyminidict/opener.py
pyminidict/pyminidict.py
pyminidict.egg-info/PKG-INFO
pyminidict.egg-info/SOURCES.txt
pyminidict.egg-info/dependency_links.txt
pyminidict.egg-info/not-zip-safe
pyminidict.egg-info/requires.txt
pyminidict.egg-info/top_level.txt