Metadata-Version: 1.1
Name: pyminidict
Version: 0.1.0
Summary: A mini CLI English/Chinese dictionary
Home-page: http://github.com/DanielBlack/pyminidict
Author: DanielBlack
Author-email: danielblack@danielblack.name
License: MIT
Platform: UNKNOWN
Classifier: Development Status :: 3 - Alpha
Classifier: Environment :: X11 Applications
Classifier: Intended Audience :: End Users/Desktop
Classifier: License :: OSI Approved :: MIT License
Classifier: Operating System :: OS Independent
Classifier: Programming Language :: Python
Classifier: Programming Language :: Python :: 3
